ThreadPoolExecutorPlus/__init__.py
ThreadPoolExecutorPlus/thread.py
ThreadPoolExecutorPlus-0.2.2.dist-info/LICENSE
ThreadPoolExecutorPlus-0.2.2.dist-info/METADATA
ThreadPoolExecutorPlus-0.2.2.dist-info/WHEEL
ThreadPoolExecutorPlus-0.2.2.dist-info/top_level.txt
ThreadPoolExecutorPlus-0.2.2.dist-info/RECORD
